{"marc_display_ss":["<record><leader>01595nam a22003611  4500</leader><controlfield tag=\"001\">213578</controlfield><controlfield tag=\"003\">SIRSI</controlfield><controlfield tag=\"005\">20151212072501.0</controlfield><controlfield tag=\"008\">840709s1869    xx            000 0 eng d</controlfield><datafield tag=\"019\" ind1=\" \" ind2=\" \"><subfield code=\"a\">MARS</subfield></datafield><datafield tag=\"035\" ind1=\" \" ind2=\" \"><subfield code=\"a\">LIAS344744</subfield></datafield><datafield tag=\"035\" ind1=\" \" ind2=\" \"><subfield code=\"a\">(OCoLC)28351641</subfield></datafield><datafield tag=\"040\" ind1=\" \" ind2=\" \"><subfield code=\"a\">PSt</subfield><subfield code=\"c\">PSt</subfield><subfield code=\"d\">WaOLN</subfield><subfield code=\"d\">UtOrBLW</subfield></datafield><datafield tag=\"100\" ind1=\"1\" ind2=\" \"><subfield code=\"a\">Murray, W. H. H.</subfield><subfield code=\"q\">(William Henry Harrison),</subfield><subfield code=\"d\">1840-1904.</subfield></datafield><datafield tag=\"245\" ind1=\"1\" ind2=\"0\"><subfield code=\"a\">Adventures in the wilderness, or, Camp life in the Adirondacks /</subfield><subfield code=\"c\">By William H.H. Murray ...</subfield></datafield><datafield tag=\"264\" ind1=\" \" ind2=\"1\"><subfield code=\"a\">Boston :</subfield><subfield code=\"b\">Fields, Osgood &amp; co.,</subfield><subfield code=\"c\">1869.</subfield></datafield><datafield tag=\"300\" ind1=\" \" ind2=\" \"><subfield code=\"a\">vi, [7]-236 pages :</subfield><subfield code=\"b\">frontispiece, plates ;</subfield><subfield code=\"c\">18 cm</subfield></datafield><datafield tag=\"336\" ind1=\" \" ind2=\" \"><subfield code=\"a\">text</subfield><subfield code=\"b\">txt</subfield><subfield code=\"2\">rdacontent</subfield></datafield><datafield tag=\"337\" ind1=\" \" ind2=\" \"><subfield code=\"a\">unmediated</subfield><subfield code=\"b\">n</subfield><subfield code=\"2\">rdamedia</subfield></datafield><datafield tag=\"338\" ind1=\" \" ind2=\" \"><subfield code=\"a\">volume</subfield><subfield code=\"b\">nc</subfield><subfield code=\"2\">rdacarrier</subfield></datafield><datafield tag=\"500\" ind1=\" \" ind2=\" \"><subfield code=\"a\">Plates with guardsheets.</subfield></datafield><datafield tag=\"500\" ind1=\" \" ind2=\" \"><subfield code=\"a\">Some plates signed : H.F., or H. Fenn.</subfield></datafield><datafield tag=\"500\" ind1=\" \" ind2=\" \"><subfield code=\"a\">Publisher's ads, [4] p. at end.</subfield></datafield><datafield tag=\"650\" ind1=\" \" ind2=\"0\"><subfield code=\"a\">Hunting</subfield><subfield code=\"z\">New York (State)</subfield><subfield code=\"z\">Adirondack Mountains.</subfield></datafield><datafield tag=\"650\" ind1=\" \" ind2=\"0\"><subfield code=\"a\">Fishing</subfield><subfield code=\"z\">New York (State)</subfield><subfield code=\"z\">Adirondack Mountains.</subfield></datafield><datafield tag=\"651\" ind1=\" \" ind2=\"0\"><subfield code=\"a\">Adirondack Mountains (N.Y.)</subfield></datafield><datafield tag=\"700\" ind1=\"1\" ind2=\" \"><subfield code=\"a\">Fenn, Harry,</subfield><subfield code=\"d\">1838-1911.</subfield></datafield><datafield tag=\"740\" ind1=\"0\" ind2=\" \"><subfield code=\"a\">Camp-life in the Adirondacks.</subfield></datafield><datafield tag=\"830\" ind1=\" \" ind2=\"0\"><subfield code=\"a\">American fiction, 1851-1875 ;</subfield><subfield code=\"v\">no. 1766.</subfield></datafield><datafield tag=\"533\" ind1=\" \" ind2=\" \"><subfield code=\"a\">Microform.</subfield><subfield code=\"b\">Louisville, Ky.,</subfield><subfield code=\"c\">Lost Cause Press,</subfield><subfield code=\"d\">1970.</subfield><subfield code=\"e\">7 microfiches : negative ; 8 x 13 cm.</subfield><subfield code=\"f\">(L.H. Wright. American fiction, 1851-1875)</subfield><subfield code=\"v\">no. 1766.</subfield></datafield><datafield tag=\"541\" ind1=\" \" ind2=\" \"><subfield code=\"3\">Rare Books copy:</subfield><subfield code=\"c\">Gift of</subfield><subfield code=\"a\">James L. W. West III.</subfield><subfield code=\"5\">PSt</subfield></datafield><datafield tag=\"949\" ind1=\" \" ind2=\" \"><subfield code=\"a\">F127.A2M9 1869</subfield><subfield code=\"w\">LC</subfield><subfield code=\"c\">1</subfield><subfield code=\"i\">000047539662</subfield><subfield code=\"l\">RARE-BOOK</subfield><subfield code=\"m\">UP-SPECCOL</subfield><subfield code=\"r\">Y</subfield><subfield code=\"s\">Y</subfield><subfield code=\"t\">BOOK</subfield><subfield code=\"u\">11/26/2002</subfield></datafield><datafield tag=\"949\" ind1=\" \" ind2=\" \"><subfield code=\"a\">Micro 3 Microfiche</subfield><subfield code=\"w\">ASIS</subfield><subfield code=\"c\">1</subfield><subfield code=\"i\">213578-5001</subfield><subfield code=\"d\">9/1/1994</subfield><subfield code=\"l\">CATO-2</subfield><subfield code=\"m\">UP-ANNEX</subfield><subfield code=\"r\">Y</subfield><subfield code=\"s\">Y</subfield><subfield code=\"t\">MICROFORM</subfield><subfield code=\"u\">4/12/2001</subfield></datafield></record>"],"all_text_timv":["Murray, W. H. H. (William Henry Harrison), 1840-1904. Adventures in the wilderness, or, Camp life in the Adirondacks / By William H.H. Murray ... Boston : Fields, Osgood & co., 1869. vi, [7]-236 pages : frontispiece, plates ; 18 cm text txt rdacontent unmediated n rdamedia volume nc rdacarrier Plates with guardsheets. Some plates signed : H.F., or H. Fenn. Publisher's ads, [4] p. at end. Hunting New York (State) Adirondack Mountains. Fishing New York (State) Adirondack Mountains. Adirondack Mountains (N.Y.) Fenn, Harry, 1838-1911. Camp-life in the Adirondacks. American fiction, 1851-1875 ; no. 1766. Microform. Louisville, Ky., Lost Cause Press, 1970. 7 microfiches : negative ; 8 x 13 cm. (L.H. Wright. American fiction, 1851-1875) no. 1766. Rare Books copy: Gift of James L. W. West III. PSt"],"id":["213578"],"oclc_number_ssim":["28351641"],"title_tsim":["Adventures in the wilderness, or, Camp life in the Adirondacks /"],"title_245ab_tsim":["Adventures in the wilderness, or, Camp life in the Adirondacks"],"title_addl_tsim":["Adventures in the wilderness, or, Camp life in the Adirondacks /"],"title_added_entry_tsim":["Camp-life in the Adirondacks."],"title_related_tsim":["Camp-life in the Adirondacks"],"title_display_ssm":["Adventures in the wilderness, or, Camp life in the Adirondacks / By William H.H. Murray ..."],"related_title_display_ssm":["Camp-life in the Adirondacks"],"title_sort":["Adventures in the wilderness, or, Camp life in the Adirondacks"],"author_tsim":["Murray, W. H. H. (William Henry Harrison), 1840-1904."],"author_addl_tsim":["Fenn, Harry, 1838-1911."],"all_authors_facet":["Murray, W. H. H. (William Henry Harrison), 1840-1904","Fenn, Harry, 1838-1911"],"author_person_display_ssm":["Murray, W. H. H. (William Henry Harrison), 1840-1904"],"addl_author_display_ssm":["Fenn, Harry, 1838-1911"],"access_facet":["In the Library"],"format":["Microfilm/Microfiche","Book"],"publisher_manufacturer_tsim":["Fields, Osgood & co."],"pub_date_itsi":[1869],"publication_display_ssm":["Boston : Fields, Osgood & co., 1869."],"overall_imprint_display_ssm":["Boston : Fields, Osgood & co., 1869."],"pub_date_illiad_ssm":["1869"],"publisher_name_ssm":["Fields, Osgood & co."],"publication_place_ssm":["Boston"],"language_facet":["English"],"subject_tsim":["Hunting","Fishing","Adirondack Mountains (N.Y.)"],"subject_addl_tsim":["New York (State) Adirondack Mountains."],"subject_display_ssm":["Hunting—New York (State)—Adirondack Mountains","Fishing—New York (State)—Adirondack Mountains","Adirondack Mountains (N.Y.)"],"subject_facet":["Hunting—New York (State)—Adirondack Mountains","Fishing—New York (State)—Adirondack Mountains","Adirondack Mountains (N.Y.)"],"subject_topic_facet":["Hunting","Fishing","Adirondack Mountains (N.Y.)"],"subject_browse_facet":["Hunting—New York (State)—Adirondack Mountains","Fishing—New York (State)—Adirondack Mountains","Adirondack Mountains (N.Y.)"],"call_number_lc_ssm":["F127.A2M9 1869"],"lc_shelfkey":["F..0127.A2.M9--1869"],"keymap_struct":["[{\"call_number\":\"F127.A2M9 1869\",\"classification\":\"LC\",\"key\":\"F..0127.A2.M9--1869\"}]"],"phys_desc_ssm":["vi, [7]-236 pages : frontispiece, plates ; 18 cm"],"general_note_ssm":["Plates with guardsheets.","Some plates signed : H.F., or H. Fenn.","Publisher's ads, [4] p. at end."],"reproduction_note_ssm":["Microform. Louisville, Ky., Lost Cause Press, 1970. 7 microfiches : negative ; 8 x 13 cm. (L.H. Wright. American fiction, 1851-1875)"],"source_aquisition_ssm":["Rare Books copy: Gift of James L. W. West III."],"up_library_facet":["Special Collections Library"],"campus_facet":["University Park","Annex"],"library_facet":["Special Collections Library","Annex"],"location_facet":["Rare Books & Manuscripts, 1st Floor Paterno"]}
