{"marc_display_ss":["<record><leader>01451cam a2200361 a 4500</leader><controlfield tag=\"001\">3751029</controlfield><controlfield tag=\"003\">SIRSI</controlfield><controlfield tag=\"005\">20180518102817.0</controlfield><controlfield tag=\"008\">910529s1947    nyu           000 0 yid  </controlfield><datafield tag=\"010\" ind1=\" \" ind2=\" \"><subfield code=\"a\">   91826065</subfield></datafield><datafield tag=\"019\" ind1=\" \" ind2=\" \"><subfield code=\"a\">959575533</subfield><subfield code=\"a\">1011152305</subfield></datafield><datafield tag=\"035\" ind1=\" \" ind2=\" \"><subfield code=\"a\">(OCoLC)27218320</subfield><subfield code=\"z\">(OCoLC)959575533</subfield><subfield code=\"z\">(OCoLC)1011152305</subfield></datafield><datafield tag=\"040\" ind1=\" \" ind2=\" \"><subfield code=\"a\">DLC-R</subfield><subfield code=\"b\">eng</subfield><subfield code=\"c\">DLC</subfield><subfield code=\"d\">OCLCG</subfield><subfield code=\"d\">OCLCO</subfield><subfield code=\"d\">OCLCF</subfield><subfield code=\"d\">OCLCO</subfield><subfield code=\"d\">OCLCQ</subfield><subfield code=\"d\">MAYHB</subfield></datafield><datafield tag=\"050\" ind1=\"0\" ind2=\"0\"><subfield code=\"a\">BJ1287.R693</subfield><subfield code=\"b\">S54 1947</subfield></datafield><datafield tag=\"066\" ind1=\" \" ind2=\" \"><subfield code=\"c\">(2</subfield></datafield><datafield tag=\"082\" ind1=\"0\" ind2=\"4\"><subfield code=\"a\">296.36</subfield></datafield><datafield tag=\"084\" ind1=\" \" ind2=\" \"><subfield code=\"a\">6483</subfield></datafield><datafield tag=\"100\" ind1=\"1\" ind2=\" \"><subfield code=\"6\">880-01</subfield><subfield code=\"a\">Rozmarin, Aharon,</subfield><subfield code=\"d\">1896-1977.</subfield></datafield><datafield tag=\"245\" ind1=\"1\" ind2=\"3\"><subfield code=\"6\">880-02</subfield><subfield code=\"a\">Di shehnḳayṭ fun Idenṭum /</subfield><subfield code=\"c\">fun Aharon Rozmarin.</subfield></datafield><datafield tag=\"260\" ind1=\" \" ind2=\" \"><subfield code=\"6\">880-03</subfield><subfield code=\"a\">Nyu Yorḳ, N.Y. :</subfield><subfield code=\"b\">Om Poblishing Ḳo.,</subfield><subfield code=\"c\">707 [1947]</subfield></datafield><datafield tag=\"300\" ind1=\" \" ind2=\" \"><subfield code=\"a\">155 pages ;</subfield><subfield code=\"c\">23 cm</subfield></datafield><datafield tag=\"336\" ind1=\" \" ind2=\" \"><subfield code=\"a\">text</subfield><subfield code=\"b\">txt</subfield><subfield code=\"2\">rdacontent</subfield></datafield><datafield tag=\"337\" ind1=\" \" ind2=\" \"><subfield code=\"a\">unmediated</subfield><subfield code=\"b\">n</subfield><subfield code=\"2\">rdamedia</subfield></datafield><datafield tag=\"338\" ind1=\" \" ind2=\" \"><subfield code=\"a\">volume</subfield><subfield code=\"b\">nc</subfield><subfield code=\"2\">rdacarrier</subfield></datafield><datafield tag=\"546\" ind1=\" \" ind2=\" \"><subfield code=\"a\">In Yiddish.</subfield></datafield><datafield tag=\"650\" ind1=\" \" ind2=\"0\"><subfield code=\"a\">Jewish ethics.</subfield></datafield><datafield tag=\"650\" ind1=\" \" ind2=\"0\"><subfield code=\"a\">Judaism</subfield><subfield code=\"x\">Essence, genius, nature.</subfield></datafield><datafield tag=\"650\" ind1=\" \" ind2=\"7\"><subfield code=\"a\">Jewish ethics.</subfield><subfield code=\"2\">fast</subfield><subfield code=\"0\">(OCoLC)fst01199497</subfield></datafield><datafield tag=\"650\" ind1=\" \" ind2=\"7\"><subfield code=\"a\">Judaism</subfield><subfield code=\"x\">Essence, genius, nature.</subfield><subfield code=\"2\">fast</subfield><subfield code=\"0\">(OCoLC)fst00984306</subfield></datafield><datafield tag=\"880\" ind1=\"1\" ind2=\" \"><subfield code=\"6\">100-01/(2/r</subfield><subfield code=\"a\">ראזמארין, אהרן.</subfield></datafield><datafield tag=\"880\" ind1=\"1\" ind2=\"0\"><subfield code=\"6\">245-02/(2/r</subfield><subfield code=\"a\">די שעהנקייט פון אידענטום /</subfield><subfield code=\"c\">פון אהרן ראזמארין.</subfield></datafield><datafield tag=\"880\" ind1=\" \" ind2=\" \"><subfield code=\"6\">260-03/(2/r</subfield><subfield code=\"a\">נוי יארק, נ.י. :</subfield><subfield code=\"b\">אום פאבלישינג קא.,</subfield><subfield code=\"c\">707 [1947].</subfield></datafield><datafield tag=\"949\" ind1=\" \" ind2=\" \"><subfield code=\"a\">BJ1287.R693S54 1947</subfield><subfield code=\"w\">LC</subfield><subfield code=\"c\">1</subfield><subfield code=\"i\">000060676856</subfield><subfield code=\"d\">2/21/2013</subfield><subfield code=\"e\">4/1/2009</subfield><subfield code=\"l\">PATTEE-BA</subfield><subfield code=\"m\">UP-PAT</subfield><subfield code=\"r\">Y</subfield><subfield code=\"s\">Y</subfield><subfield code=\"t\">BOOK</subfield><subfield code=\"u\">4/13/2007</subfield></datafield></record>"],"all_text_timv":["880-01 Rozmarin, Aharon, 1896-1977. 880-02 Di shehnḳayṭ fun Idenṭum / fun Aharon Rozmarin. 880-03 Nyu Yorḳ, N.Y. : Om Poblishing Ḳo., 707 [1947] 155 pages ; 23 cm text txt rdacontent unmediated n rdamedia volume nc rdacarrier In Yiddish. Jewish ethics. Judaism Essence, genius, nature. Jewish ethics. fast (OCoLC)fst01199497 Judaism Essence, genius, nature. fast (OCoLC)fst00984306 100-01/(2/r ראזמארין, אהרן. 245-02/(2/r די שעהנקייט פון אידענטום / פון אהרן ראזמארין. 260-03/(2/r נוי יארק, נ.י. : אום פאבלישינג קא., 707 [1947]."],"id":["3751029"],"oclc_number_ssim":["27218320"],"deprecated_oclcs_tsim":["959575533","1011152305"],"lccn_ssim":["91826065"],"title_tsim":["Di shehnḳayṭ fun Idenṭum /","די שעהנקייט פון אידענטום /"],"title_245ab_tsim":["Di shehnḳayṭ fun Idenṭum","די שעהנקייט פון אידענטום"],"title_addl_tsim":["Di shehnḳayṭ fun Idenṭum /","די שעהנקייט פון אידענטום /"],"title_latin_display_ssm":["Di shehnḳayṭ fun Idenṭum / fun Aharon Rozmarin"],"title_display_ssm":["די שעהנקייט פון אידענטום / פון אהרן ראזמארין"],"title_sort":["shehnḳayṭ fun Idenṭum"],"author_tsim":["Rozmarin, Aharon, 1896-1977.","ראזמארין, אהרן."],"all_authors_facet":["Rozmarin, Aharon, 1896-1977","ראזמארין, אהרן"],"author_person_display_ssm":["Rozmarin, Aharon, 1896-1977","ראזמארין, אהרן"],"access_facet":["In the Library"],"format":["Book"],"publisher_manufacturer_tsim":["Om Poblishing Ḳo.","אום פאבלישינג קא."],"pub_date_itsi":[1947],"publication_display_ssm":["Nyu Yorḳ, N.Y. : Om Poblishing Ḳo., 707 [1947]","נוי יארק, נ.י. : אום פאבלישינג קא., 707 [1947]."],"overall_imprint_display_ssm":["Nyu Yorḳ, N.Y. : Om Poblishing Ḳo., 707 [1947]","נוי יארק, נ.י. : אום פאבלישינג קא., 707 [1947]."],"pub_date_illiad_ssm":["707 [1947]","707 [1947]."],"publisher_name_ssm":["Om Poblishing Ḳo.","אום פאבלישינג קא."],"publication_place_ssm":["Nyu Yorḳ, N.Y.","נוי יארק, נ.י."],"language_facet":["Yiddish"],"subject_tsim":["Jewish ethics.","Judaism"],"subject_addl_tsim":["Essence, genius, nature."],"subject_display_ssm":["Jewish ethics","Judaism—Essence, genius, nature"],"subject_facet":["Jewish ethics","Judaism—Essence, genius, nature"],"subject_topic_facet":["Jewish ethics","Judaism","Essence, genius, nature"],"subject_browse_facet":["Judaism—Essence, genius, nature"],"lc_1letter_facet":["B - Philosophy, Psychology, Religion"],"lc_rest_facet":["BJ - Ethics"],"call_number_lc_ssm":["BJ1287.R693S54 1947"],"lc_shelfkey":["BJ.1287.R693.S54--1947"],"keymap_struct":["[{\"call_number\":\"BJ1287.R693S54 1947\",\"classification\":\"LC\",\"key\":\"BJ.1287.R693.S54--1947\"}]"],"phys_desc_ssm":["155 pages ; 23 cm"],"language_note_ssm":["In Yiddish."],"up_library_facet":["Pattee Library and Paterno Library Stacks"],"campus_facet":["University Park"],"library_facet":["Pattee Library and Paterno Library Stacks"],"location_facet":["Pattee - Stacks BA"]}
